README.md
setup.cfg
setup.py
seer/__init__.py
seer/client.py
seer/seer_pb2.py
seer/seer_pb2_grpc.py
seer.egg-info/PKG-INFO
seer.egg-info/SOURCES.txt
seer.egg-info/dependency_links.txt
seer.egg-info/requires.txt
seer.egg-info/top_level.txt