Metadata-Version: 1.2
Name: seer
Version: 0.1.1
Summary: Python client for cshenton/seer
Home-page: https://github.com/cshenton/seer-python
Author: Charles Shenton
Author-email: charlieshenton@me.com
License: Apache 2.0
Platform: MacOS X
Platform: Windows
Platform: Linux
Classifier: Intended Audience :: Developers
Classifier: Natural Language :: English
Classifier: License :: OSI Approved :: Apache Software License
Classifier: Programming Language :: Python :: 2
Classifier: Programming Language :: Python :: 2.7
Classifier: Programming Language :: Python :: 3
Classifier: Programming Language :: Python :: 3.4
Classifier: Programming Language :: Python :: 3.5
Classifier: Programming Language :: Python :: 3.6
Requires-Python: >=2.7, !=3.0.*, !=3.1.*, !=3.2.*
